LICENSE
MANIFEST.in
requirements.txt
setup.cfg
setup.py
test_requirements.txt
eth_contract_registry/__init__.py
eth_contract_registry/encoding.py
eth_contract_registry/interface.py
eth_contract_registry/registry.py
eth_contract_registry.egg-info/PKG-INFO
eth_contract_registry.egg-info/SOURCES.txt
eth_contract_registry.egg-info/dependency_links.txt
eth_contract_registry.egg-info/entry_points.txt
eth_contract_registry.egg-info/requires.txt
eth_contract_registry.egg-info/top_level.txt
eth_contract_registry/data/Registry.bin
eth_contract_registry/data/Registry.json
eth_contract_registry/data/Registry.metadata.json
eth_contract_registry/pytest/__init__.py
eth_contract_registry/pytest/fixtures_registry.py
eth_contract_registry/runnable/list.py
eth_contract_registry/runnable/publish.py
eth_contract_registry/runnable/set.py
eth_contract_registry/unittest/base.py
tests/test_basic.py