Metadata-Version: 2.1
Name: eth-contract-registry
Version: 0.11.0
Summary: Ethereum Smart Contract key-value registry
Home-page: https://holbrook.no/src/eth-contract-registry/log.html
Author: Louis Holbrook
Author-email: dev@holbrook.no
License: AGPL3+
Keywords: cryptocurrency,ethereum,smartcontracts
Classifier: Programming Language :: Python :: 3
Classifier: Operating System :: OS Independent
Classifier: Development Status :: 4 - Beta
Classifier: Environment :: Console
Classifier: Intended Audience :: Developers
Classifier: License :: OSI Approved :: GNU Affero General Public License v3 or later (AGPLv3+)
Classifier: Topic :: Software Development :: Libraries
Classifier: Topic :: Internet
Requires-Python: >=3.8
License-File: LICENSE
